csinscapp/__init__.py
csinscapp-0.1.6.dist-info/LICENSE
csinscapp-0.1.6.dist-info/METADATA
csinscapp-0.1.6.dist-info/WHEEL
csinscapp-0.1.6.dist-info/top_level.txt
csinscapp-0.1.6.dist-info/RECORD
